<?xml version="1.0"?>
<Element><Play><TimeCode>2019.08.01 00:20:03:17</TimeCode><Channel>OASYS1</Channel><ScheduleID></ScheduleID><EventName></EventName><FileName>F:\Media\F\MLInclude\INFO\INFO_6_2019-08-01_00-20.mp4</FileName><TrimIn>0</TrimIn><Commercial>False</Commercial><Notes></Notes></Play><Play><TimeCode>2019.08.01 00:20:38:18</TimeCode><Channel>OASYS1</Channel><ScheduleID></ScheduleID><EventName></EventName><FileName>F:\Media\F\Archive_16_9\VELU\VELU00214.mp4</FileName><TrimIn>0</TrimIn><Commercial>False</Commercial><Notes></Notes></Play>
<Play><TimeCode>2019.08.01 00:26:09:09</TimeCode><Channel>OASYS1</Channel><ScheduleID></ScheduleID><EventName></EventName><FileName>F:\Media\F\Archive_16_9\VELU\VELU00314.mp4</FileName><TrimIn>0</TrimIn><Commercial>False</Commercial><Notes></Notes></Play>
<Play><TimeCode>2019.08.01 00:34:16:12</TimeCode><Channel>OASYS1</Channel><ScheduleID></ScheduleID><EventName></EventName><FileName>F:\Media\F\MLInclude\Graphics\ident 169\Music_2019.mp4</FileName><TrimIn>0</TrimIn><Commercial>False</Commercial><Notes></Notes></Play>
<Play><TimeCode>2019.08.01 00:34:25:12</TimeCode><Channel>OASYS1</Channel><ScheduleID></ScheduleID><EventName></EventName><FileName>F:\Media\F\Archive_16_9\CLMU\CLMU05014.mp4</FileName><TrimIn>0</TrimIn><Commercial>False</Commercial><Notes></Notes></Play>
<Play><TimeCode>2019.08.01 00:37:20:11</TimeCode><Channel>OASYS1</Channel><ScheduleID></ScheduleID><EventName></EventName><FileName>F:\Media\F\MLInclude\Graphics\ident 169\ident_nebo_nich.mp4</FileName><TrimIn>0</TrimIn><Commercial>False</Commercial><Notes></Notes></Play>
<Play><TimeCode>2019.08.01 00:37:26:12</TimeCode><Channel>OASYS1</Channel><ScheduleID></ScheduleID><EventName></EventName><FileName>F:\Media\F\Archive_16_9\VELU\VELU00414.mp4</FileName><TrimIn>0</TrimIn><Commercial>False</Commercial><Notes></Notes></Play>
<Play><TimeCode>2019.08.01 00:45:50:11</TimeCode><Channel>OASYS1</Channel><ScheduleID></ScheduleID><EventName></EventName><FileName>F:\Media\F\Archive_16_9\VELU\VELU00514.mp4</FileName><TrimIn>0</TrimIn><Commercial>False</Commercial><Notes></Notes></Play>
<Play><TimeCode>2019.08.01 00:51:53:06</TimeCode><Channel>OASYS1</Channel><ScheduleID></ScheduleID><EventName></EventName><FileName>F:\Media\F\Archive_16_9\VELU\VELU00614.mp4</FileName><TrimIn>0</TrimIn><Commercial>False</Commercial><Notes></Notes></Play>
<Play><TimeCode>2019.08.01 00:58:57:22</TimeCode><Channel>OASYS1</Channel><ScheduleID></ScheduleID><EventName></EventName><FileName>F:\Media\F\MLInclude\Graphics\ident 169\ident_nebo_nich.mp4</FileName><TrimIn>0</TrimIn><Commercial>False</Commercial><Notes></Notes></Play>
<Play><TimeCode>2019.08.01 00:59:03:23</TimeCode><Channel>OASYS1</Channel><ScheduleID></ScheduleID><EventName></EventName><FileName>F:\Media\F\MLInclude\manually added files\DCHU00418.mp4</FileName><TrimIn>0</TrimIn><Commercial>False</Commercial><Notes></Notes></Play>
<Play><TimeCode>2019.08.01 01:11:30:11</TimeCode><Channel>OASYS1</Channel><ScheduleID></ScheduleID><EventName></EventName><FileName>F:\Media\F\MLInclude\Graphics\ident 169\ident_nebo_nich.mp4</FileName><TrimIn>0</TrimIn><Commercial>False</Commercial><Notes></Notes></Play>
<Play><TimeCode>2019.08.01 01:11:36:12</TimeCode><Channel>OASYS1</Channel><ScheduleID></ScheduleID><EventName></EventName><FileName>F:\Media\F\Archive_16_9\IWLU\IWLU01417.mp4</FileName><TrimIn>0</TrimIn><Commercial>False</Commercial><Notes></Notes></Play>
<Play><TimeCode>2019.08.01 01:42:29:06</TimeCode><Channel>OASYS1</Channel><ScheduleID></ScheduleID><EventName></EventName><FileName>F:\Media\F\MLInclude\INFO\INFO_3_2019-08-01_01-30.mp4</FileName><TrimIn>0</TrimIn><Commercial>False</Commercial><Notes></Notes></Play>
<Play><TimeCode>2019.08.01 01:42:57:06</TimeCode><Channel>OASYS1</Channel><ScheduleID></ScheduleID><EventName></EventName><FileName>F:\Media\F\Archive_16_9\SMKU\SMKU02816.mp4</FileName><TrimIn>0</TrimIn><Commercial>False</Commercial><Notes></Notes></Play>
<ClockResync><TimeCode>2019.08.01 02:22:45:23</TimeCode><Channel>OASYS1</Channel><Amount>4</Amount></ClockResync>
<Play><TimeCode>2019.08.01 02:59:54:18</TimeCode><Channel>OASYS1</Channel><ScheduleID></ScheduleID><EventName></EventName><FileName>F:\Media\F\MLInclude\Graphics\ident 169\ident_nebo_nich.mp4</FileName><TrimIn>0</TrimIn><Commercial>False</Commercial><Notes></Notes></Play>
<Play><TimeCode>2019.08.01 03:00:00:19</TimeCode><Channel>OASYS1</Channel><ScheduleID></ScheduleID><EventName></EventName><FileName>F:\Media\F\Archive_16_9\RCCU\RCCU02815.mp4</FileName><TrimIn>0</TrimIn><Commercial>False</Commercial><Notes></Notes></Play>
<Play><TimeCode>2019.08.01 03:27:37:19</TimeCode><Channel>OASYS1</Channel><ScheduleID></ScheduleID><EventName></EventName><FileName>F:\Media\F\MLInclude\Graphics\ident 169\ADV_IN_NEW.mp4</FileName><TrimIn>0</TrimIn><Commercial>False</Commercial><Notes></Notes></Play>
<Play><TimeCode>2019.08.01 03:27:46:19</TimeCode><Channel>OASYS1</Channel><ScheduleID></ScheduleID><EventName></EventName><FileName>F:\Media\F\Archive_16_9\ADUU\ADUU05313.mp4</FileName><TrimIn>0</TrimIn><Commercial>False</Commercial><Notes></Notes></Play>
<Play><TimeCode>2019.08.01 03:30:03:07</TimeCode><Channel>OASYS1</Channel><ScheduleID></ScheduleID><EventName></EventName><FileName>F:\Media\F\MLInclude\Graphics\ident 169\ADV_OUT_NEW.mp4</FileName><TrimIn>0</TrimIn><Commercial>False</Commercial><Notes></Notes></Play>
<Play><TimeCode>2019.08.01 03:30:12:07</TimeCode><Channel>OASYS1</Channel><ScheduleID></ScheduleID><EventName></EventName><FileName>F:\Media\F\MLInclude\manualy added files\NHCU02619.mp4</FileName><TrimIn>0</TrimIn><Commercial>False</Commercial><Notes></Notes></Play>
<Play><TimeCode>2019.08.01 04:10:50:18</TimeCode><Channel>OASYS1</Channel><ScheduleID></ScheduleID><EventName></EventName><FileName>F:\Media\F\MLInclude\INFO\INFO_6_2019-08-01_04-10.mp4</FileName><TrimIn>0</TrimIn><Commercial>False</Commercial><Notes></Notes></Play>
<Play><TimeCode>2019.08.01 04:11:25:19</TimeCode><Channel>OASYS1</Channel><ScheduleID></ScheduleID><EventName></EventName><FileName>F:\Media\F\MLInclude\manually added files\CMVU00219.mp4</FileName><TrimIn>0</TrimIn><Commercial>False</Commercial><Notes></Notes></Play>
<Play><TimeCode>2019.08.01 04:27:23:01</TimeCode><Channel>OASYS1</Channel><ScheduleID></ScheduleID><EventName></EventName><FileName>F:\Media\F\MLInclude\Graphics\ident 169\Music_2019.mp4</FileName><TrimIn>0</TrimIn><Commercial>False</Commercial><Notes></Notes></Play>
<Play><TimeCode>2019.08.01 04:27:32:01</TimeCode><Channel>OASYS1</Channel><ScheduleID></ScheduleID><EventName></EventName><FileName>F:\Media\F\Archive_16_9\JKLU\JKLU02114.mp4</FileName><TrimIn>0</TrimIn><Commercial>False</Commercial><Notes></Notes></Play>
<Play><TimeCode>2019.08.01 04:30:03:00</TimeCode><Channel>OASYS1</Channel><ScheduleID></ScheduleID><EventName></EventName><FileName>F:\Media\F\MLInclude\Graphics\ident 169\Music_2019.mp4</FileName><TrimIn>0</TrimIn><Commercial>False</Commercial><Notes></Notes></Play>
<Play><TimeCode>2019.08.01 04:30:12:00</TimeCode><Channel>OASYS1</Channel><ScheduleID></ScheduleID><EventName></EventName><FileName>F:\Media\F\Archive_16_9\JKLU\JKLU02115.mp4</FileName><TrimIn>0</TrimIn><Commercial>False</Commercial><Notes></Notes></Play>
<Play><TimeCode>2019.08.01 04:33:18:01</TimeCode><Channel>OASYS1</Channel><ScheduleID></ScheduleID><EventName></EventName><FileName>F:\Media\F\MLInclude\Graphics\ident 169\ident_nebo_nich.mp4</FileName><TrimIn>0</TrimIn><Commercial>False</Commercial><Notes></Notes></Play>
<Play><TimeCode>2019.08.01 04:33:24:02</TimeCode><Channel>OASYS1</Channel><ScheduleID></ScheduleID><EventName></EventName><FileName>F:\Media\F\Archive_16_9\OLZU\OLZU00317.mp4</FileName><TrimIn>0</TrimIn><Commercial>False</Commercial><Notes></Notes></Play>
<ClockResync><TimeCode>2019.08.01 05:12:30:24</TimeCode><Channel>OASYS1</Channel><Amount>4</Amount></ClockResync>
<Play><TimeCode>2019.08.01 05:20:30:11</TimeCode><Channel>OASYS1</Channel><ScheduleID></ScheduleID><EventName></EventName><FileName>F:\Media\F\MLInclude\Graphics\ident 169\Music_2019.mp4</FileName><TrimIn>0</TrimIn><Commercial>False</Commercial><Notes></Notes></Play>
<Play><TimeCode>2019.08.01 05:20:39:11</TimeCode><Channel>OASYS1</Channel><ScheduleID></ScheduleID><EventName></EventName><FileName>F:\Media\F\Archive_16_9\JKLU\JKLU02116.mp4</FileName><TrimIn>0</TrimIn><Commercial>False</Commercial><Notes></Notes></Play>
<Play><TimeCode>2019.08.01 05:22:58:19</TimeCode><Channel>OASYS1</Channel><ScheduleID></ScheduleID><EventName></EventName><FileName>F:\Media\F\MLInclude\Graphics\ident 169\Music_2019.mp4</FileName><TrimIn>0</TrimIn><Commercial>False</Commercial><Notes></Notes></Play>
<Play><TimeCode>2019.08.01 05:23:07:19</TimeCode><Channel>OASYS1</Channel><ScheduleID></ScheduleID><EventName></EventName><FileName>F:\Media\F\Archive_16_9\JKLU\JKLU02214.mp4</FileName><TrimIn>0</TrimIn><Commercial>False</Commercial><Notes></Notes></Play>
<Play><TimeCode>2019.08.01 05:25:46:03</TimeCode><Channel>OASYS1</Channel><ScheduleID></ScheduleID><EventName></EventName><FileName>F:\Media\F\MLInclude\Graphics\ident 169\Music_2019.mp4</FileName><TrimIn>0</TrimIn><Commercial>False</Commercial><Notes></Notes></Play>
<Play><TimeCode>2019.08.01 05:25:55:03</TimeCode><Channel>OASYS1</Channel><ScheduleID></ScheduleID><EventName></EventName><FileName>F:\Media\F\Archive_16_9\JKLU\JKLU02215.mp4</FileName><TrimIn>0</TrimIn><Commercial>False</Commercial><Notes></Notes></Play>
<Play><TimeCode>2019.08.01 05:29:36:21</TimeCode><Channel>OASYS1</Channel><ScheduleID></ScheduleID><EventName></EventName><FileName>F:\Media\F\MLInclude\Graphics\ident 169\ident_nebo_nich.mp4</FileName><TrimIn>0</TrimIn><Commercial>False</Commercial><Notes></Notes></Play>
<Play><TimeCode>2019.08.01 05:29:42:22</TimeCode><Channel>OASYS1</Channel><ScheduleID></ScheduleID><EventName></EventName><FileName>F:\Media\F\MLInclude\manually added files\MTLU00618.mp4</FileName><TrimIn>0</TrimIn><Commercial>False</Commercial><Notes></Notes></Play>
<Play><TimeCode>2019.08.01 05:59:13:10</TimeCode><Channel>OASYS1</Channel><ScheduleID></ScheduleID><EventName></EventName><FileName>F:\Media\F\MLInclude\Graphics\ident 169\ADV_IN_NEW.mp4</FileName><TrimIn>0</TrimIn><Commercial>False</Commercial><Notes></Notes></Play>
<Play><TimeCode>2019.08.01 05:59:22:10</TimeCode><Channel>OASYS1</Channel><ScheduleID></ScheduleID><EventName></EventName><FileName>F:\Media\F\Archive_16_9\ADUU\ADUU01115.mp4</FileName><TrimIn>0</TrimIn><Commercial>False</Commercial><Notes></Notes></Play>
<Play><TimeCode>2019.08.01 05:59:54:17</TimeCode><Channel>OASYS1</Channel><ScheduleID></ScheduleID><EventName></EventName><FileName>F:\Media\F\MLInclude\manually added files\ADUU00119.mp4</FileName><TrimIn>0</TrimIn><Commercial>False</Commercial><Notes></Notes></Play>
<Play><TimeCode>2019.08.01 06:00:26:00</TimeCode><Channel>OASYS1</Channel><ScheduleID></ScheduleID><EventName></EventName><FileName>F:\Media\F\MLInclude\manually added files\PFCU14018.mp4</FileName><TrimIn>0</TrimIn><Commercial>False</Commercial><Notes></Notes></Play>
<Play><TimeCode>2019.08.01 06:01:25:20</TimeCode><Channel>OASYS1</Channel><ScheduleID></ScheduleID><EventName></EventName><FileName>F:\Media\F\MLInclude\manually added files\PRUU03518.mp4</FileName><TrimIn>0</TrimIn><Commercial>False</Commercial><Notes></Notes></Play>
<Play><TimeCode>2019.08.01 06:01:56:08</TimeCode><Channel>OASYS1</Channel><ScheduleID></ScheduleID><EventName></EventName><FileName>F:\Media\F\MLInclude\Graphics\ident 169\ADV_OUT_NEW.mp4</FileName><TrimIn>0</TrimIn><Commercial>False</Commercial><Notes></Notes></Play>
<Play><TimeCode>2019.08.01 06:02:05:08</TimeCode><Channel>OASYS1</Channel><ScheduleID></ScheduleID><EventName></EventName><FileName>F:\Media\F\MLInclude\INFO\INFO_3_2019-08-01_06-00.mp4</FileName><TrimIn>0</TrimIn><Commercial>False</Commercial><Notes></Notes></Play>
<Play><TimeCode>2019.08.01 06:02:33:08</TimeCode><Channel>OASYS1</Channel><ScheduleID></ScheduleID><EventName></EventName><FileName>F:\Media\F\MLInclude\manually added files\PGBU01718.mp4</FileName><TrimIn>0</TrimIn><Commercial>False</Commercial><Notes></Notes></Play>
<Play><TimeCode>2019.08.01 06:22:04:22</TimeCode><Channel>OASYS1</Channel><ScheduleID></ScheduleID><EventName></EventName><FileName>F:\Media\F\MLInclude\Graphics\ident 169\ident_sonyach.mp4</FileName><TrimIn>0</TrimIn><Commercial>False</Commercial><Notes></Notes></Play>
<Play><TimeCode>2019.08.01 06:22:10:23</TimeCode><Channel>OASYS1</Channel><ScheduleID></ScheduleID><EventName></EventName><FileName>F:\Media\F\MLInclude\manually added files\NCTU00219.mp4</FileName><TrimIn>0</TrimIn><Commercial>False</Commercial><Notes></Notes></Play>
<Play><TimeCode>2019.08.01 06:28:43:02</TimeCode><Channel>OASYS1</Channel><ScheduleID></ScheduleID><EventName></EventName><FileName>F:\Media\F\MLInclude\Graphics\ident 169\ADV_IN_NEW.mp4</FileName><TrimIn>0</TrimIn><Commercial>False</Commercial><Notes></Notes></Play>
<Play><TimeCode>2019.08.01 06:28:52:02</TimeCode><Channel>OASYS1</Channel><ScheduleID></ScheduleID><EventName></EventName><FileName>F:\Media\F\MLInclude\manually added files\ADUU00119.mp4</FileName><TrimIn>0</TrimIn><Commercial>False</Commercial><Notes></Notes></Play>
<Play><TimeCode>2019.08.01 06:29:23:10</TimeCode><Channel>OASYS1</Channel><ScheduleID></ScheduleID><EventName></EventName><FileName>F:\Media\F\MLInclude\Graphics\ident 169\ADV_OUT_NEW.mp4</FileName><TrimIn>0</TrimIn><Commercial>False</Commercial><Notes></Notes></Play>
<Play><TimeCode>2019.08.01 06:29:32:10</TimeCode><Channel>OASYS1</Channel><ScheduleID></ScheduleID><EventName></EventName><FileName>F:\Media\F\MLInclude\manually added files\NCTU00219.mp4</FileName><TrimIn>9804</TrimIn><Commercial>False</Commercial><Notes></Notes></Play>
<Play><TimeCode>2019.08.01 06:37:08:01</TimeCode><Channel>OASYS1</Channel><ScheduleID></ScheduleID><EventName></EventName><FileName>F:\Media\F\MLInclude\Graphics\ident 169\Music_2019.mp4</FileName><TrimIn>0</TrimIn><Commercial>False</Commercial><Notes></Notes></Play>
<Play><TimeCode>2019.08.01 06:37:17:01</TimeCode><Channel>OASYS1</Channel><ScheduleID></ScheduleID><EventName></EventName><FileName>F:\Media\F\Archive_16_9\JKLU\JKLU02216.mp4</FileName><TrimIn>0</TrimIn><Commercial>False</Commercial><Notes></Notes></Play>
<Play><TimeCode>2019.08.01 06:41:54:14</TimeCode><Channel>OASYS1</Channel><ScheduleID></ScheduleID><EventName></EventName><FileName>F:\Media\F\MLInclude\Graphics\ident 169\Music_2019.mp4</FileName><TrimIn>0</TrimIn><Commercial>False</Commercial><Notes></Notes></Play>
<Play><TimeCode>2019.08.01 06:42:03:14</TimeCode><Channel>OASYS1</Channel><ScheduleID></ScheduleID><EventName></EventName><FileName>F:\Media\F\Archive_16_9\JKLU\JKLU02314.mp4</FileName><TrimIn>0</TrimIn><Commercial>False</Commercial><Notes></Notes></Play>
<Play><TimeCode>2019.08.01 06:45:21:05</TimeCode><Channel>OASYS1</Channel><ScheduleID></ScheduleID><EventName></EventName><FileName>F:\Media\F\MLInclude\Graphics\ident 169\Music_2019.mp4</FileName><TrimIn>0</TrimIn><Commercial>False</Commercial><Notes></Notes></Play>
<Play><TimeCode>2019.08.01 06:45:30:05</TimeCode><Channel>OASYS1</Channel><ScheduleID></ScheduleID><EventName></EventName><FileName>F:\Media\F\Archive_16_9\JKLU\JKLU02315.mp4</FileName><TrimIn>0</TrimIn><Commercial>False</Commercial><Notes></Notes></Play>
<Play><TimeCode>2019.08.01 06:49:09:04</TimeCode><Channel>OASYS1</Channel><ScheduleID></ScheduleID><EventName></EventName><FileName>F:\Media\F\MLInclude\Graphics\ident 169\ident_sonyach.mp4</FileName><TrimIn>0</TrimIn><Commercial>False</Commercial><Notes></Notes></Play>
<Play><TimeCode>2019.08.01 06:49:15:05</TimeCode><Channel>OASYS1</Channel><ScheduleID></ScheduleID><EventName></EventName><FileName>F:\Media\F\MLInclude\manually added files\CMVU00219.mp4</FileName><TrimIn>0</TrimIn><Commercial>False</Commercial><Notes></Notes></Play>
<Play><TimeCode>2019.08.01 07:05:12:12</TimeCode><Channel>OASYS1</Channel><ScheduleID></ScheduleID><EventName></EventName><FileName>F:\Media\F\MLInclude\Graphics\ident 169\ADV_IN_NEW.mp4</FileName><TrimIn>0</TrimIn><Commercial>False</Commercial><Notes></Notes></Play>
<Play><TimeCode>2019.08.01 07:05:21:12</TimeCode><Channel>OASYS1</Channel><ScheduleID></ScheduleID><EventName></EventName><FileName>F:\Media\F\Archive_16_9\ADUU\ADUU01115.mp4</FileName><TrimIn>0</TrimIn><Commercial>False</Commercial><Notes></Notes></Play>
<Play><TimeCode>2019.08.01 07:05:53:19</TimeCode><Channel>OASYS1</Channel><ScheduleID></ScheduleID><EventName></EventName><FileName>F:\Media\F\MLInclude\manually added files\ADUU00119.mp4</FileName><TrimIn>0</TrimIn><Commercial>False</Commercial><Notes></Notes></Play>
<Play><TimeCode>2019.08.01 07:06:25:02</TimeCode><Channel>OASYS1</Channel><ScheduleID></ScheduleID><EventName></EventName><FileName>F:\Media\F\MLInclude\manually added files\PFCU14218.mp4</FileName><TrimIn>0</TrimIn><Commercial>False</Commercial><Notes></Notes></Play>
<Play><TimeCode>2019.08.01 07:07:46:01</TimeCode><Channel>OASYS1</Channel><ScheduleID></ScheduleID><EventName></EventName><FileName>F:\Media\F\MLInclude\manually added files\PRUU03618.mp4</FileName><TrimIn>0</TrimIn><Commercial>False</Commercial><Notes></Notes></Play>
<Play><TimeCode>2019.08.01 07:08:13:07</TimeCode><Channel>OASYS1</Channel><ScheduleID></ScheduleID><EventName></EventName><FileName>F:\Media\F\MLInclude\Graphics\ident 169\ADV_OUT_NEW.mp4</FileName><TrimIn>0</TrimIn><Commercial>False</Commercial><Notes></Notes></Play>
<Play><TimeCode>2019.08.01 07:08:22:07</TimeCode><Channel>OASYS1</Channel><ScheduleID></ScheduleID><EventName></EventName><FileName>F:\Media\F\MLInclude\INFO\INFO_6_2019-08-01_07-00.mp4</FileName><TrimIn>0</TrimIn><Commercial>False</Commercial><Notes></Notes></Play>
<Play><TimeCode>2019.08.01 07:08:57:08</TimeCode><Channel>OASYS1</Channel><ScheduleID></ScheduleID><EventName></EventName><FileName>F:\Media\F\Archive_16_9\OLZU\OLZU00317.mp4</FileName><TrimIn>0</TrimIn><Commercial>False</Commercial><Notes></Notes></Play>
<Play><TimeCode>2019.08.01 07:23:51:13</TimeCode><Channel>OASYS1</Channel><ScheduleID></ScheduleID><EventName></EventName><FileName>F:\Media\F\MLInclude\Anons\SWKU00819-anons-today.mp4</FileName><TrimIn>0</TrimIn><Commercial>False</Commercial><Notes></Notes></Play>
<Play><TimeCode>2019.08.01 07:24:21:04</TimeCode><Channel>OASYS1</Channel><ScheduleID></ScheduleID><EventName></EventName><FileName>F:\Media\F\MLInclude\Anons\EPLU03318-anons-today.mp4</FileName><TrimIn>0</TrimIn><Commercial>False</Commercial><Notes></Notes></Play>
<Play><TimeCode>2019.08.01 07:24:50:10</TimeCode><Channel>OASYS1</Channel><ScheduleID></ScheduleID><EventName></EventName><FileName>F:\Media\F\Archive_16_9\OLZU\OLZU00317.mp4</FileName><TrimIn>22355</TrimIn><Commercial>False</Commercial><Notes></Notes></Play>
<Play><TimeCode>2019.08.01 07:38:50:21</TimeCode><Channel>OASYS1</Channel><ScheduleID></ScheduleID><EventName></EventName><FileName>F:\Media\F\MLInclude\Anons\ANYU00818-anons-today.mp4</FileName><TrimIn>0</TrimIn><Commercial>False</Commercial><Notes></Notes></Play>
<Play><TimeCode>2019.08.01 07:39:14:22</TimeCode><Channel>OASYS1</Channel><ScheduleID></ScheduleID><EventName></EventName><FileName>F:\Media\F\Archive_16_9\OLZU\OLZU00317.mp4</FileName><TrimIn>43366</TrimIn><Commercial>False</Commercial><Notes></Notes></Play>
<ClockResync><TimeCode>2019.08.01 07:53:05:07</TimeCode><Channel>OASYS1</Channel><Amount>4</Amount></ClockResync>
<Play><TimeCode>2019.08.01 07:57:26:15</TimeCode><Channel>OASYS1</Channel><ScheduleID></ScheduleID><EventName></EventName><FileName>F:\Media\F\MLInclude\Graphics\ident 169\Music_2019.mp4</FileName><TrimIn>0</TrimIn><Commercial>False</Commercial><Notes></Notes></Play>
<Play><TimeCode>2019.08.01 07:57:35:15</TimeCode><Channel>OASYS1</Channel><ScheduleID></ScheduleID><EventName></EventName><FileName>F:\Media\F\Archive_16_9\JKLU\JKLU02316.mp4</FileName><TrimIn>0</TrimIn><Commercial>False</Commercial><Notes></Notes></Play>
<Play><TimeCode>2019.08.01 08:01:23:23</TimeCode><Channel>OASYS1</Channel><ScheduleID></ScheduleID><EventName></EventName><FileName>F:\Media\F\MLInclude\Graphics\ident 169\Music_2019.mp4</FileName><TrimIn>0</TrimIn><Commercial>False</Commercial><Notes></Notes></Play>
<Play><TimeCode>2019.08.01 08:01:32:23</TimeCode><Channel>OASYS1</Channel><ScheduleID></ScheduleID><EventName></EventName><FileName>F:\Media\F\Archive_16_9\JKLU\JKLU02414.mp4</FileName><TrimIn>0</TrimIn><Commercial>False</Commercial><Notes></Notes></Play>
<Play><TimeCode>2019.08.01 08:02:55:15</TimeCode><Channel>OASYS1</Channel><ScheduleID></ScheduleID><EventName></EventName><FileName>F:\Media\F\MLInclude\Graphics\ident 169\ident_sonyach.mp4</FileName><TrimIn>0</TrimIn><Commercial>False</Commercial><Notes></Notes></Play>
<Play><TimeCode>2019.08.01 08:03:01:16</TimeCode><Channel>OASYS1</Channel><ScheduleID></ScheduleID><EventName></EventName><FileName>F:\Media\F\Archive_16_9\MBVU\MBVU01716.mp4</FileName><TrimIn>0</TrimIn><Commercial>False</Commercial><Notes></Notes></Play>
<Play><TimeCode>2019.08.01 08:20:59:14</TimeCode><Channel>OASYS1</Channel><ScheduleID></ScheduleID><EventName></EventName><FileName>F:\Media\F\MLInclude\Graphics\ident 169\ident_sonyach.mp4</FileName><TrimIn>0</TrimIn><Commercial>False</Commercial><Notes></Notes></Play>
<Play><TimeCode>2019.08.01 08:21:05:15</TimeCode><Channel>OASYS1</Channel><ScheduleID></ScheduleID><EventName></EventName><FileName>F:\Media\F\MLInclude\manually added files\ISLU00318.mp4</FileName><TrimIn>0</TrimIn><Commercial>False</Commercial><Notes></Notes></Play>
<Play><TimeCode>2019.08.01 08:33:27:13</TimeCode><Channel>OASYS1</Channel><ScheduleID></ScheduleID><EventName></EventName><FileName>F:\Media\F\MLInclude\Anons\SWKU00819-anons-today.mp4</FileName><TrimIn>0</TrimIn><Commercial>False</Commercial><Notes></Notes></Play>
<Play><TimeCode>2019.08.01 08:33:57:04</TimeCode><Channel>OASYS1</Channel><ScheduleID></ScheduleID><EventName></EventName><FileName>F:\Media\F\MLInclude\Anons\EPLU03318-anons-today.mp4</FileName><TrimIn>0</TrimIn><Commercial>False</Commercial><Notes></Notes></Play>
<Play><TimeCode>2019.08.01 08:34:26:10</TimeCode><Channel>OASYS1</Channel><ScheduleID></ScheduleID><EventName></EventName><FileName>F:\Media\F\MLInclude\manually added files\ISLU00318.mp4</FileName><TrimIn>18548</TrimIn><Commercial>False</Commercial><Notes></Notes></Play>
<Play><TimeCode>2019.08.01 08:44:02:02</TimeCode><Channel>OASYS1</Channel><ScheduleID></ScheduleID><EventName></EventName><FileName>F:\Media\F\MLInclude\Anons\ANYU00818-anons-today.mp4</FileName><TrimIn>0</TrimIn><Commercial>False</Commercial><Notes></Notes></Play>
<Play><TimeCode>2019.08.01 08:44:26:03</TimeCode><Channel>OASYS1</Channel><ScheduleID></ScheduleID><EventName></EventName><FileName>F:\Media\F\MLInclude\manually added files\ISLU00318.mp4</FileName><TrimIn>32940</TrimIn><Commercial>False</Commercial><Notes></Notes></Play>
<Play><TimeCode>2019.08.01 08:54:37:06</TimeCode><Channel>OASYS1</Channel><ScheduleID></ScheduleID><EventName></EventName><FileName>F:\Media\F\MLInclude\Graphics\ident 169\ADV_IN_NEW.mp4</FileName><TrimIn>0</TrimIn><Commercial>False</Commercial><Notes></Notes></Play>
<Play><TimeCode>2019.08.01 08:54:46:06</TimeCode><Channel>OASYS1</Channel><ScheduleID></ScheduleID><EventName></EventName><FileName>F:\Media\F\Archive_16_9\ADUU\ADUU01115.mp4</FileName><TrimIn>0</TrimIn><Commercial>False</Commercial><Notes></Notes></Play>
<Play><TimeCode>2019.08.01 08:55:18:13</TimeCode><Channel>OASYS1</Channel><ScheduleID></ScheduleID><EventName></EventName><FileName>F:\Media\F\MLInclude\manually added files\ADUU00119.mp4</FileName><TrimIn>0</TrimIn><Commercial>False</Commercial><Notes></Notes></Play>
<Play><TimeCode>2019.08.01 08:55:49:21</TimeCode><Channel>OASYS1</Channel><ScheduleID></ScheduleID><EventName></EventName><FileName>F:\Media\F\MLInclude\manually added files\PFCU14018.mp4</FileName><TrimIn>0</TrimIn><Commercial>False</Commercial><Notes></Notes></Play>
<Play><TimeCode>2019.08.01 08:56:49:16</TimeCode><Channel>OASYS1</Channel><ScheduleID></ScheduleID><EventName></EventName><FileName>F:\Media\F\MLInclude\manually added files\PRUU03718.mp4</FileName><TrimIn>0</TrimIn><Commercial>False</Commercial><Notes></Notes></Play>
<Play><TimeCode>2019.08.01 08:57:19:18</TimeCode><Channel>OASYS1</Channel><ScheduleID></ScheduleID><EventName></EventName><FileName>F:\Media\F\MLInclude\Graphics\ident 169\ADV_OUT_NEW.mp4</FileName><TrimIn>0</TrimIn><Commercial>False</Commercial><Notes></Notes></Play>
<Play><TimeCode>2019.08.01 08:57:28:18</TimeCode><Channel>OASYS1</Channel><ScheduleID></ScheduleID><EventName></EventName><FileName>F:\Media\F\MLInclude\Graphics\ident 169\Music_2019.mp4</FileName><TrimIn>0</TrimIn><Commercial>False</Commercial><Notes></Notes></Play>
<Play><TimeCode>2019.08.01 08:57:37:18</TimeCode><Channel>OASYS1</Channel><ScheduleID></ScheduleID><EventName></EventName><FileName>F:\Media\F\Archive_16_9\JKLU\JKLU02415.mp4</FileName><TrimIn>0</TrimIn><Commercial>False</Commercial><Notes></Notes></Play>
<Play><TimeCode>2019.08.01 08:59:33:14</TimeCode><Channel>OASYS1</Channel><ScheduleID></ScheduleID><EventName></EventName><FileName>F:\Media\F\MLInclude\Graphics\ident 169\Music_2019.mp4</FileName><TrimIn>0</TrimIn><Commercial>False</Commercial><Notes></Notes></Play>
<Play><TimeCode>2019.08.01 08:59:42:14</TimeCode><Channel>OASYS1</Channel><ScheduleID></ScheduleID><EventName></EventName><FileName>F:\Media\F\Archive_16_9\JKLU\JKLU02416.mp4</FileName><TrimIn>0</TrimIn><Commercial>False</Commercial><Notes></Notes></Play>
<Play><TimeCode>2019.08.01 09:03:27:07</TimeCode><Channel>OASYS1</Channel><ScheduleID></ScheduleID><EventName></EventName><FileName>F:\Media\F\MLInclude\INFO\INFO_3_2019-08-01_09-00.mp4</FileName><TrimIn>0</TrimIn><Commercial>False</Commercial><Notes></Notes></Play>
<Play><TimeCode>2019.08.01 09:03:55:07</TimeCode><Channel>OASYS1</Channel><ScheduleID></ScheduleID><EventName></EventName><FileName>F:\Media\F\MLInclude\manually added files\SWKU00619.mp4</FileName><TrimIn>0</TrimIn><Commercial>False</Commercial><Notes></Notes></Play>
<Play><TimeCode>2019.08.01 09:24:23:16</TimeCode><Channel>OASYS1</Channel><ScheduleID></ScheduleID><EventName></EventName><FileName>F:\Media\F\MLInclude\Anons\SWKU00819-anons-today.mp4</FileName><TrimIn>0</TrimIn><Commercial>False</Commercial><Notes></Notes></Play>
<Play><TimeCode>2019.08.01 09:24:53:07</TimeCode><Channel>OASYS1</Channel><ScheduleID></ScheduleID><EventName></EventName><FileName>F:\Media\F\MLInclude\Anons\EPLU03318-anons-today.mp4</FileName><TrimIn>0</TrimIn><Commercial>False</Commercial><Notes></Notes></Play>
<Play><TimeCode>2019.08.01 09:25:22:13</TimeCode><Channel>OASYS1</Channel><ScheduleID></ScheduleID><EventName></EventName><FileName>F:\Media\F\MLInclude\Anons\ANYU00818-anons-today.mp4</FileName><TrimIn>0</TrimIn><Commercial>False</Commercial><Notes></Notes></Play>
<Play><TimeCode>2019.08.01 09:25:46:14</TimeCode><Channel>OASYS1</Channel><ScheduleID></ScheduleID><EventName></EventName><FileName>F:\Media\F\MLInclude\manually added files\SWKU00619.mp4</FileName><TrimIn>30709</TrimIn><Commercial>False</Commercial><Notes></Notes></Play>
<Play><TimeCode>2019.08.01 10:04:46:22</TimeCode><Channel>OASYS1</Channel><ScheduleID></ScheduleID><EventName></EventName><FileName>F:\Media\F\MLInclude\Anons\SWKU00719-anons-main.mp4</FileName><TrimIn>0</TrimIn><Commercial>False</Commercial><Notes></Notes></Play>
<Play><TimeCode>2019.08.01 10:05:21:17</TimeCode><Channel>OASYS1</Channel><ScheduleID></ScheduleID><EventName></EventName><FileName>F:\Media\F\MLInclude\Graphics\ident 169\Music_new.mp4</FileName><TrimIn>0</TrimIn><Commercial>False</Commercial><Notes></Notes></Play>
<Play><TimeCode>2019.08.01 10:05:30:17</TimeCode><Channel>OASYS1</Channel><ScheduleID></ScheduleID><EventName></EventName><FileName>F:\Media\F\Archive_16_9\JMLU\JMLU00615.mp4</FileName><TrimIn>0</TrimIn><Commercial>False</Commercial><Notes></Notes></Play>
<ClockResync><TimeCode>2019.08.01 10:42:48:08</TimeCode><Channel>OASYS1</Channel><Amount>4</Amount></ClockResync>
<Play><TimeCode>2019.08.01 11:00:39:00</TimeCode><Channel>OASYS1</Channel><ScheduleID></ScheduleID><EventName></EventName><FileName>F:\Media\F\MLInclude\Graphics\ident 169\ident_sonyach.mp4</FileName><TrimIn>0</TrimIn><Commercial>False</Commercial><Notes></Notes></Play>
<Play><TimeCode>2019.08.01 11:00:45:01</TimeCode><Channel>OASYS1</Channel><ScheduleID></ScheduleID><EventName></EventName><FileName>F:\Media\F\Archive_16_9\OLZU\OLZU00317.mp4</FileName><TrimIn>0</TrimIn><Commercial>False</Commercial><Notes></Notes></Play>
<Play><TimeCode>2019.08.01 11:15:39:06</TimeCode><Channel>OASYS1</Channel><ScheduleID></ScheduleID><EventName></EventName><FileName>F:\Media\F\MLInclude\Anons\SWKU00819-anons-today.mp4</FileName><TrimIn>0</TrimIn><Commercial>False</Commercial><Notes></Notes></Play>
<Play><TimeCode>2019.08.01 11:16:08:22</TimeCode><Channel>OASYS1</Channel><ScheduleID></ScheduleID><EventName></EventName><FileName>F:\Media\F\MLInclude\Anons\EPLU03318-anons-today.mp4</FileName><TrimIn>0</TrimIn><Commercial>False</Commercial><Notes></Notes></Play>
<Play><TimeCode>2019.08.01 11:16:38:03</TimeCode><Channel>OASYS1</Channel><ScheduleID></ScheduleID><EventName></EventName><FileName>F:\Media\F\Archive_16_9\OLZU\OLZU00317.mp4</FileName><TrimIn>22355</TrimIn><Commercial>False</Commercial><Notes></Notes></Play>
<Play><TimeCode>2019.08.01 11:30:38:14</TimeCode><Channel>OASYS1</Channel><ScheduleID></ScheduleID><EventName></EventName><FileName>F:\Media\F\MLInclude\Anons\ANYU00818-anons-today.mp4</FileName><TrimIn>0</TrimIn><Commercial>False</Commercial><Notes></Notes></Play>
<Play><TimeCode>2019.08.01 11:31:02:15</TimeCode><Channel>OASYS1</Channel><ScheduleID></ScheduleID><EventName></EventName><FileName>F:\Media\F\Archive_16_9\OLZU\OLZU00317.mp4</FileName><TrimIn>43366</TrimIn><Commercial>False</Commercial><Notes></Notes></Play>
<Play><TimeCode>2019.08.01 11:49:14:04</TimeCode><Channel>OASYS1</Channel><ScheduleID></ScheduleID><EventName></EventName><FileName>F:\Media\F\MLInclude\Graphics\ident 169\ADV_IN_NEW.mp4</FileName><TrimIn>0</TrimIn><Commercial>False</Commercial><Notes></Notes></Play>
<Play><TimeCode>2019.08.01 11:49:23:04</TimeCode><Channel>OASYS1</Channel><ScheduleID></ScheduleID><EventName></EventName><FileName>F:\Media\F\Archive_16_9\ADUU\ADUU01115.mp4</FileName><TrimIn>0</TrimIn><Commercial>False</Commercial><Notes></Notes></Play>
<Play><TimeCode>2019.08.01 11:49:55:11</TimeCode><Channel>OASYS1</Channel><ScheduleID></ScheduleID><EventName></EventName><FileName>F:\Media\F\MLInclude\manually added files\ADUU00119.mp4</FileName><TrimIn>0</TrimIn><Commercial>False</Commercial><Notes></Notes></Play>
<Play><TimeCode>2019.08.01 11:50:26:19</TimeCode><Channel>OASYS1</Channel><ScheduleID></ScheduleID><EventName></EventName><FileName>F:\Media\F\MLInclude\manually added files\PFCU14318.mp4</FileName><TrimIn>0</TrimIn><Commercial>False</Commercial><Notes></Notes></Play>
<Play><TimeCode>2019.08.01 11:52:06:02</TimeCode><Channel>OASYS1</Channel><ScheduleID></ScheduleID><EventName></EventName><FileName>F:\Media\F\MLInclude\manually added files\PRUU02018.mp4</FileName><TrimIn>0</TrimIn><Commercial>False</Commercial><Notes></Notes></Play>
<Play><TimeCode>2019.08.01 11:52:38:14</TimeCode><Channel>OASYS1</Channel><ScheduleID></ScheduleID><EventName></EventName><FileName>F:\Media\F\MLInclude\Graphics\ident 169\ADV_OUT_NEW.mp4</FileName><TrimIn>0</TrimIn><Commercial>False</Commercial><Notes></Notes></Play>
<Play><TimeCode>2019.08.01 11:52:47:14</TimeCode><Channel>OASYS1</Channel><ScheduleID></ScheduleID><EventName></EventName><FileName>F:\Media\F\MLInclude\Graphics\ident 169\Music_2019.mp4</FileName><TrimIn>0</TrimIn><Commercial>False</Commercial><Notes></Notes></Play>
<Play><TimeCode>2019.08.01 11:52:56:14</TimeCode><Channel>OASYS1</Channel><ScheduleID></ScheduleID><EventName></EventName><FileName>F:\Media\F\Archive_16_9\JKLU\JKLU02514.mp4</FileName><TrimIn>0</TrimIn><Commercial>False</Commercial><Notes></Notes></Play>
<Play><TimeCode>2019.08.01 11:57:22:16</TimeCode><Channel>OASYS1</Channel><ScheduleID></ScheduleID><EventName></EventName><FileName>F:\Media\F\MLInclude\Graphics\ident 169\Music_2019.mp4</FileName><TrimIn>0</TrimIn><Commercial>False</Commercial><Notes></Notes></Play>
<Play><TimeCode>2019.08.01 11:57:31:16</TimeCode><Channel>OASYS1</Channel><ScheduleID></ScheduleID><EventName></EventName><FileName>F:\Media\F\Archive_16_9\JKLU\JKLU02515.mp4</FileName><TrimIn>0</TrimIn><Commercial>False</Commercial><Notes></Notes></Play>
<Play><TimeCode>2019.08.01 12:01:43:11</TimeCode><Channel>OASYS1</Channel><ScheduleID></ScheduleID><EventName></EventName><FileName>F:\Media\F\MLInclude\Graphics\ident 169\Music_2019.mp4</FileName><TrimIn>0</TrimIn><Commercial>False</Commercial><Notes></Notes></Play>
<Play><TimeCode>2019.08.01 12:01:52:11</TimeCode><Channel>OASYS1</Channel><ScheduleID></ScheduleID><EventName></EventName><FileName>F:\Media\F\Archive_16_9\JKLU\JKLU02516.mp4</FileName><TrimIn>0</TrimIn><Commercial>False</Commercial><Notes></Notes></Play>
<Play><TimeCode>2019.08.01 12:05:41:22</TimeCode><Channel>OASYS1</Channel><ScheduleID></ScheduleID><EventName></EventName><FileName>F:\Media\F\MLInclude\INFO\INFO_6_2019-08-01_12-00.mp4</FileName><TrimIn>0</TrimIn><Commercial>False</Commercial><Notes></Notes></Play>
<Play><TimeCode>2019.08.01 12:06:16:23</TimeCode><Channel>OASYS1</Channel><ScheduleID></ScheduleID><EventName></EventName><FileName>F:\Media\F\Archive_16_9\RCCU\RCCU02815.mp4</FileName><TrimIn>0</TrimIn><Commercial>False</Commercial><Notes></Notes></Play>
<Play><TimeCode>2019.08.01 12:21:31:10</TimeCode><Channel>OASYS1</Channel><ScheduleID></ScheduleID><EventName></EventName><FileName>F:\Media\F\MLInclude\Anons\SWKU00819-anons-today.mp4</FileName><TrimIn>0</TrimIn><Commercial>False</Commercial><Notes></Notes></Play>
<Play><TimeCode>2019.08.01 12:22:01:01</TimeCode><Channel>OASYS1</Channel><ScheduleID></ScheduleID><EventName></EventName><FileName>F:\Media\F\MLInclude\Anons\EPLU03318-anons-today.mp4</FileName><TrimIn>0</TrimIn><Commercial>False</Commercial><Notes></Notes></Play>
<Play><TimeCode>2019.08.01 12:22:30:07</TimeCode><Channel>OASYS1</Channel><ScheduleID></ScheduleID><EventName></EventName><FileName>F:\Media\F\MLInclude\Anons\ANYU00818-anons-today.mp4</FileName><TrimIn>0</TrimIn><Commercial>False</Commercial><Notes></Notes></Play>
<Play><TimeCode>2019.08.01 12:22:54:08</TimeCode><Channel>OASYS1</Channel><ScheduleID></ScheduleID><EventName></EventName><FileName>F:\Media\F\Archive_16_9\RCCU\RCCU02815.mp4</FileName><TrimIn>22862</TrimIn><Commercial>False</Commercial><Notes></Notes></Play>
<Play><TimeCode>2019.08.01 12:35:16:21</TimeCode><Channel>OASYS1</Channel><ScheduleID></ScheduleID><EventName></EventName><FileName>F:\Media\F\MLInclude\Anons\RCCU02915-anons-main.mp4</FileName><TrimIn>0</TrimIn><Commercial>False</Commercial><Notes></Notes></Play>
<Play><TimeCode>2019.08.01 12:35:59:04</TimeCode><Channel>OASYS1</Channel><ScheduleID></ScheduleID><EventName></EventName><FileName>F:\Media\F\MLInclude\Graphics\ident 169\ident_sonyach.mp4</FileName><TrimIn>0</TrimIn><Commercial>False</Commercial><Notes></Notes></Play>
<Play><TimeCode>2019.08.01 12:36:05:05</TimeCode><Channel>OASYS1</Channel><ScheduleID></ScheduleID><EventName></EventName><FileName>F:\Media\F\Archive_16_9\IWLU\IWLU01417.mp4</FileName><TrimIn>0</TrimIn><Commercial>False</Commercial><Notes></Notes></Play>
<Play><TimeCode>2019.08.01 13:06:57:24</TimeCode><Channel>OASYS1</Channel><ScheduleID></ScheduleID><EventName></EventName><FileName>F:\Media\F\MLInclude\Graphics\ident 169\ident_sonyach.mp4</FileName><TrimIn>0</TrimIn><Commercial>False</Commercial><Notes></Notes></Play>
<Play><TimeCode>2019.08.01 13:07:04:00</TimeCode><Channel>OASYS1</Channel><ScheduleID></ScheduleID><EventName></EventName><FileName>F:\Media\F\MLInclude\manually added files\CMVU00219.mp4</FileName><TrimIn>0</TrimIn><Commercial>False</Commercial><Notes></Notes></Play>
<Play><TimeCode>2019.08.01 13:23:01:07</TimeCode><Channel>OASYS1</Channel><ScheduleID></ScheduleID><EventName></EventName><FileName>F:\Media\F\MLInclude\Graphics\ident 169\ADV_IN_NEW.mp4</FileName><TrimIn>0</TrimIn><Commercial>False</Commercial><Notes></Notes></Play>
<Play><TimeCode>2019.08.01 13:23:10:07</TimeCode><Channel>OASYS1</Channel><ScheduleID></ScheduleID><EventName></EventName><FileName>F:\Media\F\Archive_16_9\ADUU\ADUU01115.mp4</FileName><TrimIn>0</TrimIn><Commercial>False</Commercial><Notes></Notes></Play>
<ClockResync><TimeCode>2019.08.01 13:23:39:19</TimeCode><Channel>OASYS1</Channel><Amount>4</Amount></ClockResync>
<Play><TimeCode>2019.08.01 13:23:42:18</TimeCode><Channel>OASYS1</Channel><ScheduleID></ScheduleID><EventName></EventName><FileName>F:\Media\F\MLInclude\manually added files\ADUU00119.mp4</FileName><TrimIn>0</TrimIn><Commercial>False</Commercial><Notes></Notes></Play>
<Play><TimeCode>2019.08.01 13:24:14:01</TimeCode><Channel>OASYS1</Channel><ScheduleID></ScheduleID><EventName></EventName><FileName>F:\Media\F\MLInclude\manually added files\PFCU14518.mp4</FileName><TrimIn>0</TrimIn><Commercial>False</Commercial><Notes></Notes></Play>
<Play><TimeCode>2019.08.01 13:25:59:02</TimeCode><Channel>OASYS1</Channel><ScheduleID></ScheduleID><EventName></EventName><FileName>F:\Media\F\MLInclude\manually added files\PRUU02118.mp4</FileName><TrimIn>0</TrimIn><Commercial>False</Commercial><Notes></Notes></Play>
<Play><TimeCode>2019.08.01 13:26:23:13</TimeCode><Channel>OASYS1</Channel><ScheduleID></ScheduleID><EventName></EventName><FileName>F:\Media\F\MLInclude\Graphics\ident 169\ADV_OUT_NEW.mp4</FileName><TrimIn>0</TrimIn><Commercial>False</Commercial><Notes></Notes></Play>
<Play><TimeCode>2019.08.01 13:26:32:13</TimeCode><Channel>OASYS1</Channel><ScheduleID></ScheduleID><EventName></EventName><FileName>F:\Media\F\MLInclude\Graphics\ident 169\Music_2019.mp4</FileName><TrimIn>0</TrimIn><Commercial>False</Commercial><Notes></Notes></Play>
<Play><TimeCode>2019.08.01 13:26:41:13</TimeCode><Channel>OASYS1</Channel><ScheduleID></ScheduleID><EventName></EventName><FileName>F:\Media\F\Archive_16_9\JKLU\JKLU02614.mp4</FileName><TrimIn>0</TrimIn><Commercial>False</Commercial><Notes></Notes></Play>
<Play><TimeCode>2019.08.01 13:29:38:05</TimeCode><Channel>OASYS1</Channel><ScheduleID></ScheduleID><EventName></EventName><FileName>F:\Media\F\MLInclude\INFO\INFO_3_2019-08-01_13-30.mp4</FileName><TrimIn>0</TrimIn><Commercial>False</Commercial><Notes></Notes></Play>
<Play><TimeCode>2019.08.01 13:30:06:05</TimeCode><Channel>OASYS1</Channel><ScheduleID></ScheduleID><EventName></EventName><FileName>F:\Media\F\MLInclude\Graphics\ident 169\Children_2019.mp4</FileName><TrimIn>0</TrimIn><Commercial>False</Commercial><Notes></Notes></Play>
<Play><TimeCode>2019.08.01 13:30:15:05</TimeCode><Channel>OASYS1</Channel><ScheduleID></ScheduleID><EventName></EventName><FileName>F:\Media\F\Archive_16_9\LPCU\LPCU02016.mp4</FileName><TrimIn>0</TrimIn><Commercial>False</Commercial><Notes></Notes></Play>
<Play><TimeCode>2019.08.01 13:57:51:20</TimeCode><Channel>OASYS1</Channel><ScheduleID></ScheduleID><EventName></EventName><FileName>F:\Media\F\MLInclude\Graphics\ident 169\ident_sonyach.mp4</FileName><TrimIn>0</TrimIn><Commercial>False</Commercial><Notes></Notes></Play>
<Play><TimeCode>2019.08.01 13:57:57:21</TimeCode><Channel>OASYS1</Channel><ScheduleID></ScheduleID><EventName></EventName><FileName>F:\Media\F\MLInclude\manualy added files\VKLU01819.mp4</FileName><TrimIn>0</TrimIn><Commercial>False</Commercial><Notes></Notes></Play>
<Play><TimeCode>2019.08.01 14:16:42:11</TimeCode><Channel>OASYS1</Channel><ScheduleID></ScheduleID><EventName></EventName><FileName>F:\Media\F\MLInclude\Anons\SWKU00819-anons-today.mp4</FileName><TrimIn>0</TrimIn><Commercial>False</Commercial><Notes></Notes></Play>
<Play><TimeCode>2019.08.01 14:17:12:02</TimeCode><Channel>OASYS1</Channel><ScheduleID></ScheduleID><EventName></EventName><FileName>F:\Media\F\MLInclude\Anons\EPLU03318-anons-today.mp4</FileName><TrimIn>0</TrimIn><Commercial>False</Commercial><Notes></Notes></Play>
<Play><TimeCode>2019.08.01 14:17:41:08</TimeCode><Channel>OASYS1</Channel><ScheduleID></ScheduleID><EventName></EventName><FileName>F:\Media\F\MLInclude\Anons\ANYU00818-anons-today.mp4</FileName><TrimIn>0</TrimIn><Commercial>False</Commercial><Notes></Notes></Play>
<Play><TimeCode>2019.08.01 14:18:05:09</TimeCode><Channel>OASYS1</Channel><ScheduleID></ScheduleID><EventName></EventName><FileName>F:\Media\F\MLInclude\manualy added files\VKLU01819.mp4</FileName><TrimIn>28115</TrimIn><Commercial>False</Commercial><Notes></Notes></Play>
<Play><TimeCode>2019.08.01 14:56:43:21</TimeCode><Channel>OASYS1</Channel><ScheduleID></ScheduleID><EventName></EventName><FileName>F:\Media\F\MLInclude\Graphics\ident 169\ident_sonyach.mp4</FileName><TrimIn>0</TrimIn><Commercial>False</Commercial><Notes></Notes></Play>
<Play><TimeCode>2019.08.01 14:56:49:22</TimeCode><Channel>OASYS1</Channel><ScheduleID></ScheduleID><EventName></EventName><FileName>F:\Media\F\MLInclude\manually added files\EPLZ03218.mp4</FileName><TrimIn>0</TrimIn><Commercial>False</Commercial><Notes></Notes></Play>
<Play><TimeCode>2019.08.01 15:28:32:09</TimeCode><Channel>OASYS1</Channel><ScheduleID></ScheduleID><EventName></EventName><FileName>F:\Media\F\MLInclude\Graphics\ident 169\ADV_IN_NEW.mp4</FileName><TrimIn>0</TrimIn><Commercial>False</Commercial><Notes></Notes></Play>
<Play><TimeCode>2019.08.01 15:28:41:09</TimeCode><Channel>OASYS1</Channel><ScheduleID></ScheduleID><EventName></EventName><FileName>F:\Media\F\Archive_16_9\ADUU\ADUU01115.mp4</FileName><TrimIn>0</TrimIn><Commercial>False</Commercial><Notes></Notes></Play>
<Play><TimeCode>2019.08.01 15:29:13:16</TimeCode><Channel>OASYS1</Channel><ScheduleID></ScheduleID><EventName></EventName><FileName>F:\Media\F\MLInclude\manually added files\ADUU00119.mp4</FileName><TrimIn>0</TrimIn><Commercial>False</Commercial><Notes></Notes></Play>
<Play><TimeCode>2019.08.01 15:29:44:24</TimeCode><Channel>OASYS1</Channel><ScheduleID></ScheduleID><EventName></EventName><FileName>F:\Media\F\MLInclude\manually added files\PFCU14618.mp4</FileName><TrimIn>0</TrimIn><Commercial>False</Commercial><Notes></Notes></Play>
<Play><TimeCode>2019.08.01 15:31:45:15</TimeCode><Channel>OASYS1</Channel><ScheduleID></ScheduleID><EventName></EventName><FileName>F:\Media\F\MLInclude\manually added files\PRUU02218.mp4</FileName><TrimIn>0</TrimIn><Commercial>False</Commercial><Notes></Notes></Play>
<Play><TimeCode>2019.08.01 15:32:18:09</TimeCode><Channel>OASYS1</Channel><ScheduleID></ScheduleID><EventName></EventName><FileName>F:\Media\F\MLInclude\Graphics\ident 169\ADV_OUT_NEW.mp4</FileName><TrimIn>0</TrimIn><Commercial>False</Commercial><Notes></Notes></Play>
<Play><TimeCode>2019.08.01 15:32:27:09</TimeCode><Channel>OASYS1</Channel><ScheduleID></ScheduleID><EventName></EventName><FileName>F:\Media\F\MLInclude\INFO\INFO_6_2019-08-01_15-30.mp4</FileName><TrimIn>0</TrimIn><Commercial>False</Commercial><Notes></Notes></Play>
<Play><TimeCode>2019.08.01 15:33:02:10</TimeCode><Channel>OASYS1</Channel><ScheduleID></ScheduleID><EventName></EventName><FileName>F:\Media\F\MLInclude\manualy added files\NCTZ01019.mp4</FileName><TrimIn>0</TrimIn><Commercial>False</Commercial><Notes></Notes></Play>
<Play><TimeCode>2019.08.01 15:49:43:03</TimeCode><Channel>OASYS1</Channel><ScheduleID></ScheduleID><EventName></EventName><FileName>F:\Media\F\MLInclude\Graphics\ident 169\Music_new.mp4</FileName><TrimIn>0</TrimIn><Commercial>False</Commercial><Notes></Notes></Play>
<Play><TimeCode>2019.08.01 15:49:52:03</TimeCode><Channel>OASYS1</Channel><ScheduleID></ScheduleID><EventName></EventName><FileName>F:\Media\F\MLInclude\manually added files\TELU00818.mp4</FileName><TrimIn>0</TrimIn><Commercial>False</Commercial><Notes></Notes></Play>
<Play><TimeCode>2019.08.01 16:01:26:20</TimeCode><Channel>OASYS1</Channel><ScheduleID></ScheduleID><EventName></EventName><FileName>F:\Media\F\MLInclude\Anons\SWKU00819-anons-today.mp4</FileName><TrimIn>0</TrimIn><Commercial>False</Commercial><Notes></Notes></Play>
<Play><TimeCode>2019.08.01 16:01:56:11</TimeCode><Channel>OASYS1</Channel><ScheduleID></ScheduleID><EventName></EventName><FileName>F:\Media\F\MLInclude\Anons\EPLU03318-anons-today.mp4</FileName><TrimIn>0</TrimIn><Commercial>False</Commercial><Notes></Notes></Play>
<Play><TimeCode>2019.08.01 16:02:25:17</TimeCode><Channel>OASYS1</Channel><ScheduleID></ScheduleID><EventName></EventName><FileName>F:\Media\F\MLInclude\Anons\ANYU00818-anons-today.mp4</FileName><TrimIn>0</TrimIn><Commercial>False</Commercial><Notes></Notes></Play>
<Play><TimeCode>2019.08.01 16:02:49:18</TimeCode><Channel>OASYS1</Channel><ScheduleID></ScheduleID><EventName></EventName><FileName>F:\Media\F\MLInclude\manually added files\TELU00818.mp4</FileName><TrimIn>17367</TrimIn><Commercial>False</Commercial><Notes></Notes></Play>
<ClockResync><TimeCode>2019.08.01 16:13:25:15</TimeCode><Channel>OASYS1</Channel><Amount>4</Amount></ClockResync>
<Play><TimeCode>2019.08.01 16:20:28:18</TimeCode><Channel>OASYS1</Channel><ScheduleID></ScheduleID><EventName></EventName><FileName>F:\Media\F\MLInclude\Graphics\ident 169\ident_sonyach.mp4</FileName><TrimIn>0</TrimIn><Commercial>False</Commercial><Notes></Notes></Play>
<Play><TimeCode>2019.08.01 16:20:34:19</TimeCode><Channel>OASYS1</Channel><ScheduleID></ScheduleID><EventName></EventName><FileName>F:\Media\F\Archive_16_9\FKLU\FKLU00117.mp4</FileName><TrimIn>0</TrimIn><Commercial>False</Commercial><Notes></Notes></Play>
<Play><TimeCode>2019.08.01 16:38:21:11</TimeCode><Channel>OASYS1</Channel><ScheduleID></ScheduleID><EventName></EventName><FileName>F:\Media\F\MLInclude\Graphics\ident 169\ADV_IN_NEW.mp4</FileName><TrimIn>0</TrimIn><Commercial>False</Commercial><Notes></Notes></Play>
<Play><TimeCode>2019.08.01 16:38:30:11</TimeCode><Channel>OASYS1</Channel><ScheduleID></ScheduleID><EventName></EventName><FileName>F:\Media\F\Archive_16_9\ADUU\ADUU01115.mp4</FileName><TrimIn>0</TrimIn><Commercial>False</Commercial><Notes></Notes></Play>
<Play><TimeCode>2019.08.01 16:39:02:18</TimeCode><Channel>OASYS1</Channel><ScheduleID></ScheduleID><EventName></EventName><FileName>F:\Media\F\MLInclude\manually added files\ADUU00119.mp4</FileName><TrimIn>0</TrimIn><Commercial>False</Commercial><Notes></Notes></Play>
<Play><TimeCode>2019.08.01 16:39:34:01</TimeCode><Channel>OASYS1</Channel><ScheduleID></ScheduleID><EventName></EventName><FileName>F:\Media\F\MLInclude\manually added files\PFCU14718.mp4</FileName><TrimIn>0</TrimIn><Commercial>False</Commercial><Notes></Notes></Play>
<Play><TimeCode>2019.08.01 16:41:22:09</TimeCode><Channel>OASYS1</Channel><ScheduleID></ScheduleID><EventName></EventName><FileName>F:\Media\F\MLInclude\manually added files\PRUU02318.mp4</FileName><TrimIn>0</TrimIn><Commercial>False</Commercial><Notes></Notes></Play>
<Play><TimeCode>2019.08.01 16:42:00:02</TimeCode><Channel>OASYS1</Channel><ScheduleID></ScheduleID><EventName></EventName><FileName>F:\Media\F\MLInclude\Graphics\ident 169\ADV_OUT_NEW.mp4</FileName><TrimIn>0</TrimIn><Commercial>False</Commercial><Notes></Notes></Play>
<Play><TimeCode>2019.08.01 16:42:09:02</TimeCode><Channel>OASYS1</Channel><ScheduleID></ScheduleID><EventName></EventName><FileName>F:\Media\F\MLInclude\INFO\INFO_3_2019-08-01_16-40.mp4</FileName><TrimIn>0</TrimIn><Commercial>False</Commercial><Notes></Notes></Play>
<Play><TimeCode>2019.08.01 16:42:37:02</TimeCode><Channel>OASYS1</Channel><ScheduleID></ScheduleID><EventName></EventName><FileName>F:\Media\F\MLInclude\manually added files\ISLU00318.mp4</FileName><TrimIn>0</TrimIn><Commercial>False</Commercial><Notes></Notes></Play>
<Play><TimeCode>2019.08.01 16:54:59:00</TimeCode><Channel>OASYS1</Channel><ScheduleID></ScheduleID><EventName></EventName><FileName>F:\Media\F\MLInclude\Anons\SWKU00819-anons-today.mp4</FileName><TrimIn>0</TrimIn><Commercial>False</Commercial><Notes></Notes></Play>
<Play><TimeCode>2019.08.01 16:55:28:16</TimeCode><Channel>OASYS1</Channel><ScheduleID></ScheduleID><EventName></EventName><FileName>F:\Media\F\MLInclude\Anons\EPLU03318-anons-today.mp4</FileName><TrimIn>0</TrimIn><Commercial>False</Commercial><Notes></Notes></Play>
<Play><TimeCode>2019.08.01 16:55:57:22</TimeCode><Channel>OASYS1</Channel><ScheduleID></ScheduleID><EventName></EventName><FileName>F:\Media\F\MLInclude\manually added files\ISLU00318.mp4</FileName><TrimIn>18548</TrimIn><Commercial>False</Commercial><Notes></Notes></Play>
<Play><TimeCode>2019.08.01 17:05:33:14</TimeCode><Channel>OASYS1</Channel><ScheduleID></ScheduleID><EventName></EventName><FileName>F:\Media\F\MLInclude\Anons\ANYU00818-anons-today.mp4</FileName><TrimIn>0</TrimIn><Commercial>False</Commercial><Notes></Notes></Play>
<Play><TimeCode>2019.08.01 17:05:57:15</TimeCode><Channel>OASYS1</Channel><ScheduleID></ScheduleID><EventName></EventName><FileName>F:\Media\F\MLInclude\manually added files\ISLU00318.mp4</FileName><TrimIn>32940</TrimIn><Commercial>False</Commercial><Notes></Notes></Play>
<Play><TimeCode>2019.08.01 17:16:08:18</TimeCode><Channel>OASYS1</Channel><ScheduleID></ScheduleID><EventName></EventName><FileName>F:\Media\F\MLInclude\Graphics\ident 169\Music_new.mp4</FileName><TrimIn>0</TrimIn><Commercial>False</Commercial><Notes></Notes></Play>
<Play><TimeCode>2019.08.01 17:16:17:18</TimeCode><Channel>OASYS1</Channel><ScheduleID></ScheduleID><EventName></EventName><FileName>F:\Media\F\Archive_16_9\JKLU\JKLU02615.mp4</FileName><TrimIn>0</TrimIn><Commercial>False</Commercial><Notes></Notes></Play>
<Play><TimeCode>2019.08.01 17:20:22:21</TimeCode><Channel>OASYS1</Channel><ScheduleID></ScheduleID><EventName></EventName><FileName>F:\Media\F\MLInclude\Graphics\ident 169\ident_sonyach.mp4</FileName><TrimIn>0</TrimIn><Commercial>False</Commercial><Notes></Notes></Play>
<Play><TimeCode>2019.08.01 17:20:28:22</TimeCode><Channel>OASYS1</Channel><ScheduleID></ScheduleID><EventName></EventName><FileName>F:\Media\F\MLInclude\manually added files\MTLU00618.mp4</FileName><TrimIn>0</TrimIn><Commercial>False</Commercial><Notes></Notes></Play>
<Play><TimeCode>2019.08.01 17:49:59:10</TimeCode><Channel>OASYS1</Channel><ScheduleID></ScheduleID><EventName></EventName><FileName>F:\Media\F\MLInclude\Graphics\ident 169\ident_sonyach.mp4</FileName><TrimIn>0</TrimIn><Commercial>False</Commercial><Notes></Notes></Play>
<Play><TimeCode>2019.08.01 17:50:05:11</TimeCode><Channel>OASYS1</Channel><ScheduleID></ScheduleID><EventName></EventName><FileName>F:\Media\F\Archive_16_9\IWCU\IWCU00815.mp4</FileName><TrimIn>0</TrimIn><Commercial>False</Commercial><Notes></Notes></Play>
<Play><TimeCode>2019.08.01 18:13:12:07</TimeCode><Channel>OASYS1</Channel><ScheduleID></ScheduleID><EventName></EventName><FileName>F:\Media\F\MLInclude\Graphics\ident 169\ADV_IN_NEW.mp4</FileName><TrimIn>0</TrimIn><Commercial>False</Commercial><Notes></Notes></Play>
<Play><TimeCode>2019.08.01 18:13:21:07</TimeCode><Channel>OASYS1</Channel><ScheduleID></ScheduleID><EventName></EventName><FileName>F:\Media\F\Archive_16_9\ADUU\ADUU01115.mp4</FileName><TrimIn>0</TrimIn><Commercial>False</Commercial><Notes></Notes></Play>
<Play><TimeCode>2019.08.01 18:13:53:14</TimeCode><Channel>OASYS1</Channel><ScheduleID></ScheduleID><EventName></EventName><FileName>F:\Media\F\MLInclude\manually added files\ADUU00119.mp4</FileName><TrimIn>0</TrimIn><Commercial>False</Commercial><Notes></Notes></Play>
<Play><TimeCode>2019.08.01 18:14:24:22</TimeCode><Channel>OASYS1</Channel><ScheduleID></ScheduleID><EventName></EventName><FileName>F:\Media\F\MLInclude\manually added files\PFCU14818.mp4</FileName><TrimIn>0</TrimIn><Commercial>False</Commercial><Notes></Notes></Play>
<Play><TimeCode>2019.08.01 18:15:54:02</TimeCode><Channel>OASYS1</Channel><ScheduleID></ScheduleID><EventName></EventName><FileName>F:\Media\F\MLInclude\manually added files\PRUU02618.mp4</FileName><TrimIn>0</TrimIn><Commercial>False</Commercial><Notes></Notes></Play>
<Play><TimeCode>2019.08.01 18:16:22:02</TimeCode><Channel>OASYS1</Channel><ScheduleID></ScheduleID><EventName></EventName><FileName>F:\Media\F\MLInclude\Graphics\ident 169\ADV_OUT_NEW.mp4</FileName><TrimIn>0</TrimIn><Commercial>False</Commercial><Notes></Notes></Play>
<Play><TimeCode>2019.08.01 18:16:31:02</TimeCode><Channel>OASYS1</Channel><ScheduleID></ScheduleID><EventName></EventName><FileName>F:\Media\F\MLInclude\Graphics\ident 169\Music_new.mp4</FileName><TrimIn>0</TrimIn><Commercial>False</Commercial><Notes></Notes></Play>
<Play><TimeCode>2019.08.01 18:16:40:02</TimeCode><Channel>OASYS1</Channel><ScheduleID></ScheduleID><EventName></EventName><FileName>F:\Media\F\Archive_16_9\JKLU\JKLU02616.mp4</FileName><TrimIn>0</TrimIn><Commercial>False</Commercial><Notes></Notes></Play>
<Play><TimeCode>2019.08.01 18:22:26:23</TimeCode><Channel>OASYS1</Channel><ScheduleID></ScheduleID><EventName></EventName><FileName>F:\Media\F\MLInclude\INFO\INFO_6_2019-08-01_18-20.mp4</FileName><TrimIn>0</TrimIn><Commercial>False</Commercial><Notes></Notes></Play>
<Play><TimeCode>2019.08.01 18:23:01:24</TimeCode><Channel>OASYS1</Channel><ScheduleID></ScheduleID><EventName></EventName><FileName>F:\Media\F\MLInclude\manualy added files\NHCU02619.mp4</FileName><TrimIn>0</TrimIn><Commercial>False</Commercial><Notes></Notes></Play>
<ClockResync><TimeCode>2019.08.01 18:54:18:16</TimeCode><Channel>OASYS1</Channel><Amount>4</Amount></ClockResync>
<Play><TimeCode>2019.08.01 19:03:40:14</TimeCode><Channel>OASYS1</Channel><ScheduleID></ScheduleID><EventName></EventName><FileName>F:\Media\F\MLInclude\Graphics\ident 169\ident_sonyach.mp4</FileName><TrimIn>0</TrimIn><Commercial>False</Commercial><Notes></Notes></Play>
<Play><TimeCode>2019.08.01 19:03:46:15</TimeCode><Channel>OASYS1</Channel><ScheduleID></ScheduleID><EventName></EventName><FileName>F:\Media\F\MLInclude\manually added files\SWKU00819.mp4</FileName><TrimIn>0</TrimIn><Commercial>False</Commercial><Notes></Notes></Play>
<Play><TimeCode>2019.08.01 19:27:12:00</TimeCode><Channel>OASYS1</Channel><ScheduleID></ScheduleID><EventName></EventName><FileName>F:\Media\F\MLInclude\Anons\EPLU03318-anons-today.mp4</FileName><TrimIn>0</TrimIn><Commercial>False</Commercial><Notes></Notes></Play>
<Play><TimeCode>2019.08.01 19:27:41:06</TimeCode><Channel>OASYS1</Channel><ScheduleID></ScheduleID><EventName></EventName><FileName>F:\Media\F\MLInclude\Anons\ANYU00818-anons-today.mp4</FileName><TrimIn>0</TrimIn><Commercial>False</Commercial><Notes></Notes></Play>
<Play><TimeCode>2019.08.01 19:28:05:07</TimeCode><Channel>OASYS1</Channel><ScheduleID></ScheduleID><EventName></EventName><FileName>F:\Media\F\MLInclude\Anons\SNCU02018-anons-main.mp4</FileName><TrimIn>0</TrimIn><Commercial>False</Commercial><Notes></Notes></Play>
<Play><TimeCode>2019.08.01 19:28:35:05</TimeCode><Channel>OASYS1</Channel><ScheduleID></ScheduleID><EventName></EventName><FileName>F:\Media\F\MLInclude\manually added files\SWKU00819.mp4</FileName><TrimIn>35135</TrimIn><Commercial>False</Commercial><Notes></Notes></Play>
<Play><TimeCode>2019.08.01 20:01:14:24</TimeCode><Channel>OASYS1</Channel><ScheduleID></ScheduleID><EventName></EventName><FileName>F:\Media\F\MLInclude\Anons\SWKU00919-anons-main.mp4</FileName><TrimIn>0</TrimIn><Commercial>False</Commercial><Notes></Notes></Play>
<Play><TimeCode>2019.08.01 20:01:49:16</TimeCode><Channel>OASYS1</Channel><ScheduleID></ScheduleID><EventName></EventName><FileName>F:\Media\F\MLInclude\Graphics\ident 169\ident_sonyach.mp4</FileName><TrimIn>0</TrimIn><Commercial>False</Commercial><Notes></Notes></Play>
<Play><TimeCode>2019.08.01 20:01:55:17</TimeCode><Channel>OASYS1</Channel><ScheduleID></ScheduleID><EventName></EventName><FileName>F:\Media\F\MLInclude\manually added files\NCTU00219.mp4</FileName><TrimIn>0</TrimIn><Commercial>False</Commercial><Notes></Notes></Play>
<Play><TimeCode>2019.08.01 20:08:27:21</TimeCode><Channel>OASYS1</Channel><ScheduleID></ScheduleID><EventName></EventName><FileName>F:\Media\F\MLInclude\Graphics\ident 169\ADV_IN_NEW.mp4</FileName><TrimIn>0</TrimIn><Commercial>False</Commercial><Notes></Notes></Play>
<Play><TimeCode>2019.08.01 20:08:36:21</TimeCode><Channel>OASYS1</Channel><ScheduleID></ScheduleID><EventName></EventName><FileName>F:\Media\F\MLInclude\manually added files\ADUU00119.mp4</FileName><TrimIn>0</TrimIn><Commercial>False</Commercial><Notes></Notes></Play>
<Play><TimeCode>2019.08.01 20:09:08:04</TimeCode><Channel>OASYS1</Channel><ScheduleID></ScheduleID><EventName></EventName><FileName>F:\Media\F\MLInclude\Graphics\ident 169\ADV_OUT_NEW.mp4</FileName><TrimIn>0</TrimIn><Commercial>False</Commercial><Notes></Notes></Play>
<Play><TimeCode>2019.08.01 20:09:17:04</TimeCode><Channel>OASYS1</Channel><ScheduleID></ScheduleID><EventName></EventName><FileName>F:\Media\F\MLInclude\manually added files\NCTU00219.mp4</FileName><TrimIn>9804</TrimIn><Commercial>False</Commercial><Notes></Notes></Play>
<Play><TimeCode>2019.08.01 20:16:52:20</TimeCode><Channel>OASYS1</Channel><ScheduleID></ScheduleID><EventName></EventName><FileName>F:\Media\F\MLInclude\Graphics\ident 169\ADV_IN_NEW.mp4</FileName><TrimIn>0</TrimIn><Commercial>False</Commercial><Notes></Notes></Play>
<Play><TimeCode>2019.08.01 20:17:01:20</TimeCode><Channel>OASYS1</Channel><ScheduleID></ScheduleID><EventName></EventName><FileName>F:\Media\F\Archive_16_9\ADUU\ADUU01115.mp4</FileName><TrimIn>0</TrimIn><Commercial>False</Commercial><Notes></Notes></Play>
<Play><TimeCode>2019.08.01 20:17:34:02</TimeCode><Channel>OASYS1</Channel><ScheduleID></ScheduleID><EventName></EventName><FileName>F:\Media\F\MLInclude\manually added files\ADUU00119.mp4</FileName><TrimIn>0</TrimIn><Commercial>False</Commercial><Notes></Notes></Play>
<Play><TimeCode>2019.08.01 20:18:05:10</TimeCode><Channel>OASYS1</Channel><ScheduleID></ScheduleID><EventName></EventName><FileName>F:\Media\F\MLInclude\manually added files\PFCU14918.mp4</FileName><TrimIn>0</TrimIn><Commercial>False</Commercial><Notes></Notes></Play>
<Play><TimeCode>2019.08.01 20:20:06:05</TimeCode><Channel>OASYS1</Channel><ScheduleID></ScheduleID><EventName></EventName><FileName>F:\Media\F\MLInclude\manually added files\PRUU02718.mp4</FileName><TrimIn>0</TrimIn><Commercial>False</Commercial><Notes></Notes></Play>
<Play><TimeCode>2019.08.01 20:20:35:13</TimeCode><Channel>OASYS1</Channel><ScheduleID></ScheduleID><EventName></EventName><FileName>F:\Media\F\MLInclude\Graphics\ident 169\ADV_OUT_NEW.mp4</FileName><TrimIn>0</TrimIn><Commercial>False</Commercial><Notes></Notes></Play>
<Play><TimeCode>2019.08.01 20:20:44:13</TimeCode><Channel>OASYS1</Channel><ScheduleID></ScheduleID><EventName></EventName><FileName>F:\Media\F\MLInclude\Graphics\ident 169\Music_new.mp4</FileName><TrimIn>0</TrimIn><Commercial>False</Commercial><Notes></Notes></Play>
<Play><TimeCode>2019.08.01 20:20:53:13</TimeCode><Channel>OASYS1</Channel><ScheduleID></ScheduleID><EventName></EventName><FileName>F:\Media\F\Archive_16_9\JKLU\JKLU02714.mp4</FileName><TrimIn>0</TrimIn><Commercial>False</Commercial><Notes></Notes></Play>
<Play><TimeCode>2019.08.01 20:24:23:09</TimeCode><Channel>OASYS1</Channel><ScheduleID></ScheduleID><EventName></EventName><FileName>F:\Media\F\MLInclude\Graphics\ident 169\Music_new.mp4</FileName><TrimIn>0</TrimIn><Commercial>False</Commercial><Notes></Notes></Play>
<Play><TimeCode>2019.08.01 20:24:32:09</TimeCode><Channel>OASYS1</Channel><ScheduleID></ScheduleID><EventName></EventName><FileName>F:\Media\F\Archive_16_9\JKLU\JKLU02715.mp4</FileName><TrimIn>0</TrimIn><Commercial>False</Commercial><Notes></Notes></Play>
<Play><TimeCode>2019.08.01 20:28:01:00</TimeCode><Channel>OASYS1</Channel><ScheduleID></ScheduleID><EventName></EventName><FileName>F:\Media\F\MLInclude\Graphics\ident 169\Music_new.mp4</FileName><TrimIn>0</TrimIn><Commercial>False</Commercial><Notes></Notes></Play>
<Play><TimeCode>2019.08.01 20:28:10:00</TimeCode><Channel>OASYS1</Channel><ScheduleID></ScheduleID><EventName></EventName><FileName>F:\Media\F\Archive_16_9\JKLU\JKLU02716.mp4</FileName><TrimIn>0</TrimIn><Commercial>False</Commercial><Notes></Notes></Play>
<Play><TimeCode>2019.08.01 20:33:53:05</TimeCode><Channel>OASYS1</Channel><ScheduleID></ScheduleID><EventName></EventName><FileName>F:\Media\F\MLInclude\INFO\INFO_3_2019-08-01_20-30.mp4</FileName><TrimIn>0</TrimIn><Commercial>False</Commercial><Notes></Notes></Play>
<Play><TimeCode>2019.08.01 20:34:21:05</TimeCode><Channel>OASYS1</Channel><ScheduleID></ScheduleID><EventName></EventName><FileName>F:\Media\F\MLInclude\manually added files\EPLU03318.mp4</FileName><TrimIn>0</TrimIn><Commercial>False</Commercial><Notes></Notes></Play>
<Play><TimeCode>2019.08.01 20:50:31:20</TimeCode><Channel>OASYS1</Channel><ScheduleID></ScheduleID><EventName></EventName><FileName>F:\Media\F\MLInclude\Anons\ANYU00818-anons-today.mp4</FileName><TrimIn>0</TrimIn><Commercial>False</Commercial><Notes></Notes></Play>
<Play><TimeCode>2019.08.01 20:50:55:21</TimeCode><Channel>OASYS1</Channel><ScheduleID></ScheduleID><EventName></EventName><FileName>F:\Media\F\MLInclude\Anons\SNCU02018-anons-main.mp4</FileName><TrimIn>0</TrimIn><Commercial>False</Commercial><Notes></Notes></Play>
<Play><TimeCode>2019.08.01 20:51:25:19</TimeCode><Channel>OASYS1</Channel><ScheduleID></ScheduleID><EventName></EventName><FileName>F:\Media\F\MLInclude\manually added files\EPLU03318.mp4</FileName><TrimIn>24265</TrimIn><Commercial>False</Commercial><Notes></Notes></Play>
<Play><TimeCode>2019.08.01 21:00:08:08</TimeCode><Channel>OASYS1</Channel><ScheduleID></ScheduleID><EventName></EventName><FileName>F:\Media\F\MLInclude\Graphics\ident 169\ident_nebo2_nich.mp4</FileName><TrimIn>0</TrimIn><Commercial>False</Commercial><Notes></Notes></Play>
<Play><TimeCode>2019.08.01 21:00:14:09</TimeCode><Channel>OASYS1</Channel><ScheduleID></ScheduleID><EventName></EventName><FileName>F:\Media\F\Archive_16_9\ATCU\ATCU00215.mp4</FileName><TrimIn>0</TrimIn><Commercial>False</Commercial><Notes></Notes></Play>
<Play><TimeCode>2019.08.01 21:02:43:02</TimeCode><Channel>OASYS1</Channel><ScheduleID></ScheduleID><EventName></EventName><FileName>F:\Media\F\MLInclude\Graphics\ident 169\Music_new.mp4</FileName><TrimIn>0</TrimIn><Commercial>False</Commercial><Notes></Notes></Play>
<Play><TimeCode>2019.08.01 21:02:52:02</TimeCode><Channel>OASYS1</Channel><ScheduleID></ScheduleID><EventName></EventName><FileName>F:\Media\F\Archive_16_9\JKLU\JKLU02814.mp4</FileName><TrimIn>0</TrimIn><Commercial>False</Commercial><Notes></Notes></Play>
<Play><TimeCode>2019.08.01 21:07:55:10</TimeCode><Channel>OASYS1</Channel><ScheduleID></ScheduleID><EventName></EventName><FileName>F:\Media\F\MLInclude\Graphics\ident 169\Music_new.mp4</FileName><TrimIn>0</TrimIn><Commercial>False</Commercial><Notes></Notes></Play>
<Play><TimeCode>2019.08.01 21:08:04:10</TimeCode><Channel>OASYS1</Channel><ScheduleID></ScheduleID><EventName></EventName><FileName>F:\Media\F\Archive_16_9\JKLU\JKLU02815.mp4</FileName><TrimIn>0</TrimIn><Commercial>False</Commercial><Notes></Notes></Play>
<Play><TimeCode>2019.08.01 21:10:10:14</TimeCode><Channel>OASYS1</Channel><ScheduleID></ScheduleID><EventName></EventName><FileName>F:\Media\F\MLInclude\Graphics\ident 169\ident_nebo2_nich.mp4</FileName><TrimIn>0</TrimIn><Commercial>False</Commercial><Notes></Notes></Play>
<Play><TimeCode>2019.08.01 21:10:16:15</TimeCode><Channel>OASYS1</Channel><ScheduleID></ScheduleID><EventName></EventName><FileName>F:\Media\F\Archive_16_9\MBVU\MBVU01716.mp4</FileName><TrimIn>0</TrimIn><Commercial>False</Commercial><Notes></Notes></Play>
<Play><TimeCode>2019.08.01 21:28:14:13</TimeCode><Channel>OASYS1</Channel><ScheduleID></ScheduleID><EventName></EventName><FileName>F:\Media\F\MLInclude\Graphics\ident 169\ADV_IN_NEW.mp4</FileName><TrimIn>0</TrimIn><Commercial>False</Commercial><Notes></Notes></Play>
<Play><TimeCode>2019.08.01 21:28:23:13</TimeCode><Channel>OASYS1</Channel><ScheduleID></ScheduleID><EventName></EventName><FileName>F:\Media\F\Archive_16_9\ADUU\ADUU01115.mp4</FileName><TrimIn>0</TrimIn><Commercial>False</Commercial><Notes></Notes></Play>
<Play><TimeCode>2019.08.01 21:28:55:20</TimeCode><Channel>OASYS1</Channel><ScheduleID></ScheduleID><EventName></EventName><FileName>F:\Media\F\MLInclude\manually added files\ADUU00119.mp4</FileName><TrimIn>0</TrimIn><Commercial>False</Commercial><Notes></Notes></Play>
<Play><TimeCode>2019.08.01 21:29:27:03</TimeCode><Channel>OASYS1</Channel><ScheduleID></ScheduleID><EventName></EventName><FileName>F:\Media\F\MLInclude\manually added files\PFCU15018.mp4</FileName><TrimIn>0</TrimIn><Commercial>False</Commercial><Notes></Notes></Play>
<Play><TimeCode>2019.08.01 21:31:11:12</TimeCode><Channel>OASYS1</Channel><ScheduleID></ScheduleID><EventName></EventName><FileName>F:\Media\F\MLInclude\manually added files\PRUU02818.mp4</FileName><TrimIn>0</TrimIn><Commercial>False</Commercial><Notes></Notes></Play>
<Play><TimeCode>2019.08.01 21:31:37:09</TimeCode><Channel>OASYS1</Channel><ScheduleID></ScheduleID><EventName></EventName><FileName>F:\Media\F\MLInclude\Graphics\ident 169\ADV_OUT_NEW.mp4</FileName><TrimIn>0</TrimIn><Commercial>False</Commercial><Notes></Notes></Play>
<Play><TimeCode>2019.08.01 21:31:46:09</TimeCode><Channel>OASYS1</Channel><ScheduleID></ScheduleID><EventName></EventName><FileName>F:\Media\F\MLInclude\INFO\INFO_6_2019-08-01_21-30.mp4</FileName><TrimIn>0</TrimIn><Commercial>False</Commercial><Notes></Notes></Play>
<Play><TimeCode>2019.08.01 21:32:21:10</TimeCode><Channel>OASYS1</Channel><ScheduleID></ScheduleID><EventName></EventName><FileName>F:\Media\F\MLInclude\manualy added files\UMAU00818.mp4</FileName><TrimIn>0</TrimIn><Commercial>False</Commercial><Notes></Notes></Play>
<ClockResync><TimeCode>2019.08.01 21:39:28:04</TimeCode><Channel>OASYS1</Channel><Amount>4</Amount></ClockResync>
<Play><TimeCode>2019.08.01 21:56:12:04</TimeCode><Channel>OASYS1</Channel><ScheduleID></ScheduleID><EventName></EventName><FileName>F:\Media\F\MLInclude\Graphics\ident 169\Music_new.mp4</FileName><TrimIn>0</TrimIn><Commercial>False</Commercial><Notes></Notes></Play>
<Play><TimeCode>2019.08.01 21:56:21:04</TimeCode><Channel>OASYS1</Channel><ScheduleID></ScheduleID><EventName></EventName><FileName>F:\Media\F\Archive_16_9\CLMU\CLMU10112.mp4</FileName><TrimIn>0</TrimIn><Commercial>False</Commercial><Notes></Notes></Play>
<Play><TimeCode>2019.08.01 21:57:52:02</TimeCode><Channel>OASYS1</Channel><ScheduleID></ScheduleID><EventName></EventName><FileName>F:\Media\F\MLInclude\Graphics\ident 169\ident_nebo2_nich.mp4</FileName><TrimIn>0</TrimIn><Commercial>False</Commercial><Notes></Notes></Play>
<Play><TimeCode>2019.08.01 21:57:58:03</TimeCode><Channel>OASYS1</Channel><ScheduleID></ScheduleID><EventName></EventName><FileName>F:\Media\F\MLInclude\manually added files\ANYU00818.mp4</FileName><TrimIn>0</TrimIn><Commercial>False</Commercial><Notes></Notes></Play>
<Play><TimeCode>2019.08.01 22:15:07:17</TimeCode><Channel>OASYS1</Channel><ScheduleID></ScheduleID><EventName></EventName><FileName>F:\Media\F\MLInclude\Anons\SNCU02018-anons-main.mp4</FileName><TrimIn>0</TrimIn><Commercial>False</Commercial><Notes></Notes></Play>
<Play><TimeCode>2019.08.01 22:15:37:15</TimeCode><Channel>OASYS1</Channel><ScheduleID></ScheduleID><EventName></EventName><FileName>F:\Media\F\MLInclude\manually added files\ANYU00818.mp4</FileName><TrimIn>25739</TrimIn><Commercial>False</Commercial><Notes></Notes></Play>
<Play><TimeCode>2019.08.01 22:36:40:24</TimeCode><Channel>OASYS1</Channel><ScheduleID></ScheduleID><EventName></EventName><FileName>F:\Media\F\MLInclude\Anons\SNCU02018-anons-main.mp4</FileName><TrimIn>0</TrimIn><Commercial>False</Commercial><Notes></Notes></Play>
<Play><TimeCode>2019.08.01 22:37:10:22</TimeCode><Channel>OASYS1</Channel><ScheduleID></ScheduleID><EventName></EventName><FileName>F:\Media\F\MLInclude\manually added files\ANYU00818.mp4</FileName><TrimIn>57323</TrimIn><Commercial>False</Commercial><Notes></Notes></Play>
<Play><TimeCode>2019.08.01 23:01:04:12</TimeCode><Channel>OASYS1</Channel><ScheduleID></ScheduleID><EventName></EventName><FileName>F:\Media\F\Archive_16_9\DOCU\DOCU00216.mp4</FileName><TrimIn>0</TrimIn><Commercial>False</Commercial><Notes></Notes></Play>
<Play><TimeCode>2019.08.01 23:59:58:21</TimeCode><Channel>OASYS1</Channel><ScheduleID></ScheduleID><EventName></EventName><FileName>F:\Media\F\MLInclude\INFO\INFO_6_2019-08-02_00-00.mp4</FileName><TrimIn>0</TrimIn><Commercial>False</Commercial><Notes></Notes></Play>
</Element>
